LICENSE
README.md
pyproject.toml
./README.md
logger_protocol/VERSION
logger_protocol/__init__.py
logger_protocol/logger_protocol.py
logger_protocol/silent_logger.py
logger_protocol.egg-info/PKG-INFO
logger_protocol.egg-info/SOURCES.txt
logger_protocol.egg-info/dependency_links.txt
logger_protocol.egg-info/requires.txt
logger_protocol.egg-info/top_level.txt
tests/test_silent_logger.py